Workbook

Sheet APP
C11: CONFIGURAÇÕES
C12: Salário mensal | D12: 3650
C13: Rendimento médio da Carteira | D13: 0.008
C14: Sugestão de investimento (30%) | D14: =D12*30 -> 109500
C16: INVESTIMENTO MENSAL
C17: Aporte mensal | D17: 1095
C18: Prazo (anos) | D18: 6
C19: Taxa mensal | D19: 0.008
C20: Patrimônio acumulado | D20: =FV(D19,D18*12,D17*-1) -> 106055.72
C21: Dividendos mensais | D21: =D20*D13 -> 848.44579
B23: Cenários
B24: Anos | C24: Aporte mensal | D24: Patrimônio | E24: Dividendos/mês
B25: 2 | C25: =$D$17 -> 1095 | D25: =FV($D$19,B25*12,$D$17*-1) -> 28845.755 | E25: =D25*$D$13 -> 230.76604
B26: 5 | C26: =$D$17 -> 1095 | D26: =FV($D$19,B26*12,$D$17*-1) -> 83903.134 | E26: =D26*$D$13 -> 671.22507
B27: 10 | C27: =$D$17 -> 1095 | D27: =FV($D$19,B27*12,$D$17*-1) -> 219238.13 | E27: =D27*$D$13 -> 1753.905
B28: 20 | C28: =$D$17 -> 1095 | D28: =FV($D$19,B28*12,$D$17*-1) -> 789638.69 | E28: =D28*$D$13 -> 6317.1095
B32: PERFIL | C32: Moderado
B33: VALOR A SER INVESTIDO POR MÊS | C33: =D17 -> 1095
B35: TIPO DE FII | C35: Percentual Sugerido | D35: Valores
B36: PAPEL | C36: =VLOOKUP($C$32&"-"&B36,PLANILHA2!$A:$D,4,FALSE) -> 0.32 | D36: =C36*$C$33 -> 350.4
B37: TIJOLO | C37: =VLOOKUP($C$32&"-"&B37,PLANILHA2!$A:$D,4,FALSE) -> 0.35 | D37: =C37*$C$33 -> 383.25
B38: HÍBRIDOS | C38: =VLOOKUP($C$32&"-"&B38,PLANILHA2!$A:$D,4,FALSE) -> 0.08 | D38: =C38*$C$33 -> 87.6
B39: FOFs | C39: =VLOOKUP($C$32&"-"&B39,PLANILHA2!$A:$D,4,FALSE) -> 0.05 | D39: =C39*$C$33 -> 54.75
B40: DESENVOLVIMENTO | C40: =VLOOKUP($C$32&"-"&B40,PLANILHA2!$A:$D,4,FALSE) -> 0.1 | D40: =C40*$C$33 -> 109.5
B41: HOTELARIAS | C41: =VLOOKUP($C$32&"-"&B41,PLANILHA2!$A:$D,4,FALSE) -> 0.1 | D41: =C41*$C$33 -> 109.5

Sheet PLANILHA2
A2: CHAVE | B2: PERFIL | C2: TIPO DE FII | D2: %
A3: =B3&"-"&C3 -> Conservador-PAPEL | B3: Conservador | C3: PAPEL | D3: 0.3
A4: =B4&"-"&C4 -> Conservador-TIJOLO | B4: Conservador | C4: TIJOLO | D4: 0.5
A5: =B5&"-"&C5 -> Conservador-HÍBRIDOS | B5: Conservador | C5: HÍBRIDOS | D5: 0.1 | H5: %
A6: =B6&"-"&C6 -> Conservador-FOFs | B6: Conservador | C6: FOFs | D6: 0.1 | G6: Moderado-TIJOLO | H6: =VLOOKUP(G6,$A:$D,4,FALSE) -> 0.35
A7: =B7&"-"&C7 -> Conservador-DESENVOLVIMENTO | B7: Conservador | C7: DESENVOLVIMENTO | D7: 0
A8: =B8&"-"&C8 -> Conservador-HOTELARIAS | B8: Conservador | C8: HOTELARIAS | D8: 0
A9: =B9&"-"&C9 -> Moderado-PAPEL | B9: Moderado | C9: PAPEL | D9: 0.32
A10: =B10&"-"&C10 -> Moderado-TIJOLO | B10: Moderado | C10: TIJOLO | D10: 0.35
A11: =B11&"-"&C11 -> Moderado-HÍBRIDOS | B11: Moderado | C11: HÍBRIDOS | D11: 0.08
A12: =B12&"-"&C12 -> Moderado-FOFs | B12: Moderado | C12: FOFs | D12: 0.05
A13: =B13&"-"&C13 -> Moderado-DESENVOLVIMENTO | B13: Moderado | C13: DESENVOLVIMENTO | D13: 0.1
A14: =B14&"-"&C14 -> Moderado-HOTELARIAS | B14: Moderado | C14: HOTELARIAS | D14: 0.1
A15: =B15&"-"&C15 -> Agressivo-PAPEL | B15: Agressivo | C15: PAPEL | D15: 0.5
A16: =B16&"-"&C16 -> Agressivo-TIJOLO | B16: Agressivo | C16: TIJOLO | D16: 0.1
A17: =B17&"-"&C17 -> Agressivo-HÍBRIDOS | B17: Agressivo | C17: HÍBRIDOS | D17: 0.05
A18: =B18&"-"&C18 -> Agressivo-FOFs | B18: Agressivo | C18: FOFs | D18: 0.05
... A20: =B20&"-"&C20 -> Agressivo-HOTELARIAS | B20: Agressivo | C20: HOTELARIAS | D20: 0.1
C38: =PROCV($C$32&"-"&B37,PERFIS!'PERFIS '!$A:$D,4,FALSO)
